setup.py
CatalogCrawler/__init__.py
CatalogCrawler/catalog.py
CatalogCrawler/course.py
CatalogCrawler/crawler.py
CatalogCrawler/extractor.py
CatalogCrawler/pred.py
CatalogCrawler/school.py
CatalogCrawler.egg-info/PKG-INFO
CatalogCrawler.egg-info/SOURCES.txt
CatalogCrawler.egg-info/dependency_links.txt
CatalogCrawler.egg-info/not-zip-safe
CatalogCrawler.egg-info/top_level.txt