Metadata-Version: 1.0
Name: CatalogCrawler
Version: 0.1
Summary: Tools to crawl course catalogs
Home-page: UNKNOWN
Author: Ke Wang
Author-email: kewang55@gmail.com
License: MIT
Platform: UNKNOWN
